tinydrama/__init__.py
tinydrama/browser.py
tinydrama/cdp.py
tinydrama/frame.py
tinydrama-0.1.3.dist-info/METADATA
tinydrama-0.1.3.dist-info/WHEEL
tinydrama-0.1.3.dist-info/top_level.txt
tinydrama-0.1.3.dist-info/RECORD
