Metadata-Version: 2.4
Name: tinydrama
Version: 0.1.3
Summary: 轻量级浏览器自动化库，直连 Chrome CDP
Author: inshallah123
License: MIT
Project-URL: Homepage, https://github.com/inshallah123/Tinydrama
Project-URL: Repository, https://github.com/inshallah123/Tinydrama
Keywords: browser,automation,chrome,cdp,devtools
Classifier: Development Status :: 4 - Beta
Classifier: Intended Audience :: Developers
Classifier: License :: OSI Approved :: MIT License
Classifier: Programming Language :: Python :: 3
Classifier: Programming Language :: Python :: 3.8
Classifier: Programming Language :: Python :: 3.9
Classifier: Programming Language :: Python :: 3.10
Classifier: Programming Language :: Python :: 3.11
Classifier: Programming Language :: Python :: 3.12
Classifier: Operating System :: Microsoft :: Windows
Classifier: Topic :: Software Development :: Testing
Requires-Python: >=3.8
